[{"listingId":"52de3ebd5d0e57a03b00006b","type":"pbw","url":"https://www.filepicker.io/api/file/FSGsAbTRz2zuPKFfMeF5","etag":"ddc73b5c183d141406ffe64f75ad5362","contentType":"application/octet-stream","origFileName":"EliqEffect.pbw","fileName":"f51f3848-e7af-49f4-8938-83bc829e999e","sha1":"a015e23211fbba9c4bc6251319ea2012818c2945"},{"listingId":"52de3ebd5d0e57a03b00006b","type":"screenshot_images-144x168","url":"https://assets.getpebble.com/api/file/3vTqWRDoQDOClzxlehj0/convert?cache=true&fit=crop&w=144&h=168","etag":"","contentType":"","origFileName":"","fileName":"","sha1":""},{"listingId":"52de3ebd5d0e57a03b00006b","type":"screenshot_images-144x168","url":"https://assets.getpebble.com/api/file/cfFCWzLSuK6Gwxyi7z58/convert?cache=true&fit=crop&w=144&h=168","etag":"","contentType":"","origFileName":"","fileName":"","sha1":""},{"listingId":"52de3ebd5d0e57a03b00006b","type":"screenshot_images-144x168","url":"https://assets.getpebble.com/api/file/rAsZ9B5TZPezlQGAJlwQ/convert?cache=true&fit=crop&w=144&h=168","etag":"","contentType":"","origFileName":"","fileName":"","sha1":""},{"listingId":"52de3ebd5d0e57a03b00006b","type":"screenshot_images-144x168","url":"https://assets.getpebble.com/api/file/XvsIKV78QiSjWq94GuuN/convert?cache=true&fit=crop&w=144&h=168","etag":"","contentType":"","origFileName":"","fileName":"","sha1":""},{"listingId":"52de3ebd5d0e57a03b00006b","type":"list_image-80x80","url":"https://assets.getpebble.com/api/file/3vTqWRDoQDOClzxlehj0/convert?cache=true&fit=crop&w=80&h=80","etag":"","contentType":"","origFileName":"","fileName":"","sha1":""},{"listingId":"52de3ebd5d0e57a03b00006b","type":"list_image-144x144","url":"https://assets.getpebble.com/api/file/3vTqWRDoQDOClzxlehj0/convert?cache=true&fit=crop&w=144&h=144","etag":"","contentType":"","origFileName":"","fileName":"","sha1":""}]
